sphinx_easy/__init__.py
sphinx_easy/cli.py
sphinx_easy-0.1.0.dist-info/entry_points.txt
sphinx_easy-0.1.0.dist-info/METADATA
sphinx_easy-0.1.0.dist-info/WHEEL
sphinx_easy-0.1.0.dist-info/RECORD
