Metadata-Version: 2.1
Name: sphinx-easy
Version: 0.1.0
Summary: 简易 Sphinx 文档生成工具
Author: KG
Author-email: zhoukaige18@gmail.com
Requires-Python: >=3.11,<4.0
Classifier: Programming Language :: Python :: 3
Classifier: Programming Language :: Python :: 3.11
Classifier: Programming Language :: Python :: 3.12
Classifier: Programming Language :: Python :: 3.13
Requires-Dist: click (>=8.1.8,<9.0.0)
Requires-Dist: myst-parser (>=4.0.1,<5.0.0)
Requires-Dist: sphinx (>=8.2.3,<9.0.0)
Requires-Dist: sphinx-markdown-builder (>=0.6.8,<0.7.0)
